cpanel/__init__.py
cpanel/cpanel.py
cpanel/utils.py
cpanel_client-1.0.0.dist-info/LICENSE
cpanel_client-1.0.0.dist-info/METADATA
cpanel_client-1.0.0.dist-info/WHEEL
cpanel_client-1.0.0.dist-info/top_level.txt
cpanel_client-1.0.0.dist-info/RECORD
