Metadata-Version: 2.1
Name: cpanel-client
Version: 1.0.0
Summary: A Python package for interacting with WHM + cPanel
Home-page: https://github.com/smnafiz/python-cpanel-api
Author: nafiz
Author-email: sminrana@gmail.com
Project-URL: Bug Tracker, https://github.com/smnafiz/python-cpanel-api/issues
Classifier: Programming Language :: Python :: 3
Classifier: License :: OSI Approved :: MIT License
Classifier: Operating System :: OS Independent
Requires-Python: >=3.6
License-File: LICENSE
